shared_objects/Motor.py
shared_objects/ROS_utils.py
shared_objects/__init__.py
shared_objects/utils_model.py
shared_objects/utils_path.py
shared_objects/utils_stop.py
shared_objects-0.1.2.dist-info/METADATA
shared_objects-0.1.2.dist-info/WHEEL
shared_objects-0.1.2.dist-info/top_level.txt
shared_objects-0.1.2.dist-info/RECORD
