Metadata-Version: 2.1
Name: shared_objects
Version: 0.1.2
Summary: ROS2 Utils
Home-page: https://github.com/ozaydincan/shared_objects.git
Author: Can Ozaydin
Author-email: ozaydincan.app@gmail.com
License: MIT
Classifier: Programming Language :: Python :: 3
Classifier: License :: OSI Approved :: MIT License
Classifier: Operating System :: OS Independent
Requires-Python: >=3.9
